PyWave.py
PyWave-0.5.0.dist-info/LICENSE
PyWave-0.5.0.dist-info/METADATA
PyWave-0.5.0.dist-info/WHEEL
PyWave-0.5.0.dist-info/top_level.txt
PyWave-0.5.0.dist-info/RECORD
