Metadata-Version: 2.1
Name: PyWave
Version: 0.5.0
Summary: Open, read and write Wave files
Home-page: https://github.com/Zuzu-Typ/PyWave
Author: Zuzu_Typ
Author-email: zuzu.typ@gmail.com
License: zlib/libpng license
Keywords: wave RIFF wav interface simple read write create load open
Platform: UNKNOWN
Classifier: Development Status :: 5 - Production/Stable
Classifier: Intended Audience :: Developers
Classifier: Topic :: Games/Entertainment
Classifier: Topic :: Multimedia :: Sound/Audio
Classifier: Topic :: Software Development :: Libraries
Classifier: License :: OSI Approved :: zlib/libpng License
Classifier: Programming Language :: Python :: 2
Classifier: Programming Language :: Python :: 2.7
Classifier: Programming Language :: Python :: 3
Classifier: Programming Language :: Python :: 3.3
Classifier: Programming Language :: Python :: 3.4
Classifier: Programming Language :: Python :: 3.5
Classifier: Programming Language :: Python :: 3.6
Classifier: Programming Language :: Python :: 3.7
Classifier: Programming Language :: Python :: 3.8
Classifier: Programming Language :: Python :: 3.9
